process_data/__init__.py
process_data/setup.py
process_data2/__init__.py
process_data2/setup.py
process_data2-0.4.dist-info/METADATA
process_data2-0.4.dist-info/WHEEL
process_data2-0.4.dist-info/top_level.txt
process_data2-0.4.dist-info/RECORD
