Metadata-Version: 2.1
Name: process-data2
Version: 0.4
Summary: Data processing for the SEAT mobility advisor project
Home-page: UNKNOWN
Author: kenedy123
Author-email: UNKNOWN
License: MIT
Platform: UNKNOWN
